{
  "id": "91134dca",
  "symbol": "AAPL",
  "timeframe": "1H",
  "created_at": "2026-01-12T23:51:18.344992",
  "predictions": [
    {
      "period": 1,
      "label": "Hour 1",
      "direction": "DOWN",
      "confidence": 59.3
    },
    {
      "period": 2,
      "label": "Hour 2",
      "direction": "DOWN",
      "confidence": 62.8
    },
    {
      "period": 3,
      "label": "Hour 3",
      "direction": "DOWN",
      "confidence": 60.8
    },
    {
      "period": 4,
      "label": "Hour 4",
      "direction": "UP",
      "confidence": 52.8
    },
    {
      "period": 5,
      "label": "Hour 5",
      "direction": "DOWN",
      "confidence": 56.2
    }
  ],
  "ghost_candles": [
    {
      "time": "2026-01-10T20:46:00",
      "open": 167.06,
      "high": 167.28,
      "low": 165.69,
      "close": 166.15,
      "direction": "DOWN",
      "confidence": 59.3,
      "opacity": 0.4
    },
    {
      "time": "2026-01-10T21:46:00",
      "open": 166.15,
      "high": 166.2,
      "low": 164.73,
      "close": 165.21,
      "direction": "DOWN",
      "confidence": 62.8,
      "opacity": 0.35000000000000003
    },
    {
      "time": "2026-01-10T22:46:00",
      "open": 165.21,
      "high": 165.4,
      "low": 163.61,
      "close": 164.29,
      "direction": "DOWN",
      "confidence": 60.8,
      "opacity": 0.30000000000000004
    },
    {
      "time": "2026-01-10T23:46:00",
      "open": 164.29,
      "high": 165.38,
      "low": 163.38,
      "close": 165.14,
      "direction": "UP",
      "confidence": 52.8,
      "opacity": 0.25
    },
    {
      "time": "2026-01-11T00:46:00",
      "open": 165.14,
      "high": 165.72,
      "low": 163.9,
      "close": 164.26,
      "direction": "DOWN",
      "confidence": 56.2,
      "opacity": 0.2
    }
  ],
  "validated": false,
  "actual_outcome": null
}